
{
  "signals": [
    {
      "commodity": "GOLD",
      "signal": "BUY",
      "confidence": 0.82,
      "price": 62500,
      "change": 450,
      "change_percent": 0.72,
      "volume": 125000,
      "last_updated": "2025-01-12T10:30:00Z"
    },
    {
      "commodity": "SILVER",
      "signal": "HOLD",
      "confidence": 0.65,
      "price": 75200,
      "change": -120,
      "change_percent": -0.16,
      "volume": 89000,
      "last_updated": "2025-01-12T10:30:00Z"
    }
  ],
  "correlations": {
    "GOLD": {
      "SILVER": 0.78,
      "CRUDE": 0.23,
      "USD_INR": -0.45
    },
    "SILVER": {
      "GOLD": 0.78,
      "CRUDE": 0.19,
      "USD_INR": -0.38
    }
  },
  "generation_time_ms": 89,
  "last_updated": "2025-01-12T10:30:00Z"
}
